odoo10_addon_sale_line_cost_control-10.0.1.0.0.99.dev15-nspkg.pth
odoo/addons/sale_line_cost_control/README.rst
odoo/addons/sale_line_cost_control/__init__.py
odoo/addons/sale_line_cost_control/__manifest__.py
odoo/addons/sale_line_cost_control/i18n/fr.po
odoo/addons/sale_line_cost_control/i18n/hr.po
odoo/addons/sale_line_cost_control/i18n/nl_NL.po
odoo/addons/sale_line_cost_control/i18n/sale_line_cost_control.pot
odoo/addons/sale_line_cost_control/images/change-cost.png
odoo/addons/sale_line_cost_control/images/order-lines.png
odoo/addons/sale_line_cost_control/models/__init__.py
odoo/addons/sale_line_cost_control/models/sale.py
odoo/addons/sale_line_cost_control/security/security.xml
odoo/addons/sale_line_cost_control/static/description/icon.png
odoo/addons/sale_line_cost_control/tests/__init__.py
odoo/addons/sale_line_cost_control/tests/common.py
odoo/addons/sale_line_cost_control/tests/test_sale.py
odoo/addons/sale_line_cost_control/tests/test_set_sale_line_purchase_price.py
odoo/addons/sale_line_cost_control/views/sale_views.xml
odoo/addons/sale_line_cost_control/wizards/__init__.py
odoo/addons/sale_line_cost_control/wizards/set_sale_line_purchase_price.py
odoo/addons/sale_line_cost_control/wizards/set_sale_line_purchase_price_views.xml
odoo10_addon_sale_line_cost_control-10.0.1.0.0.99.dev15.dist-info/METADATA
odoo10_addon_sale_line_cost_control-10.0.1.0.0.99.dev15.dist-info/WHEEL
odoo10_addon_sale_line_cost_control-10.0.1.0.0.99.dev15.dist-info/namespace_packages.txt
odoo10_addon_sale_line_cost_control-10.0.1.0.0.99.dev15.dist-info/top_level.txt
odoo10_addon_sale_line_cost_control-10.0.1.0.0.99.dev15.dist-info/RECORD
